langchain_code/__init__.py
langchain_code/cli.py
langchain_code/config_core.py
langchain_code/hooks.py
langchain_code/mcp_loader.py
langchain_code/static_values.py
langchain_code/agent/deep_agents.py
langchain_code/agent/react.py
langchain_code/agent/state.py
langchain_code/agent/subagents.py
langchain_code/cli/__init__.py
langchain_code/cli/constants_runtime.py
langchain_code/cli/entrypoint.py
langchain_code/cli/commands/chat.py
langchain_code/cli/commands/configure.py
langchain_code/cli/commands/flows.py
langchain_code/cli/commands/system.py
langchain_code/cli_components/__init__.py
langchain_code/cli_components/agents.py
langchain_code/cli_components/app.py
langchain_code/cli_components/constants.py
langchain_code/cli_components/display.py
langchain_code/cli_components/editors.py
langchain_code/cli_components/env.py
langchain_code/cli_components/instructions.py
langchain_code/cli_components/launcher.py
langchain_code/cli_components/mcp.py
langchain_code/cli_components/runtime.py
langchain_code/cli_components/state.py
langchain_code/cli_components/todos.py
langchain_code/config/__init__.py
langchain_code/config/mcp.json
langchain_code/safety/confirm.py
langchain_code/tools/fs_local.py
langchain_code/tools/mermaid.py
langchain_code/tools/planner.py
langchain_code/tools/processor.py
langchain_code/tools/script_exec.py
langchain_code/tools/search.py
langchain_code/tools/shell.py
langchain_code/workflows/auto.py
langchain_code/workflows/base_system.py
langchain_code/workflows/bug_fix.py
langchain_code/workflows/feature_impl.py
langchain_code-0.1.5.dist-info/licenses/LICENSE
langchain_code-0.1.5.dist-info/METADATA
langchain_code-0.1.5.dist-info/WHEEL
langchain_code-0.1.5.dist-info/entry_points.txt
langchain_code-0.1.5.dist-info/top_level.txt
langchain_code-0.1.5.dist-info/RECORD
