Metadata-Version: 2.4
Name: langchain-code
Version: 0.1.5
Requires-Python: >=3.11
License-File: LICENSE
Requires-Dist: click<9,>=8.1.7
Requires-Dist: typer>=0.12.3
Requires-Dist: rich==13.7.1
Requires-Dist: python-dotenv==1.0.1
Requires-Dist: langchain>=0.2.12
Requires-Dist: langchain-community>=0.2.10
Requires-Dist: langchain-anthropic>=0.2.4
Requires-Dist: langchain-google-genai>=2.0.4
Requires-Dist: langgraph<0.4.0
Requires-Dist: pydantic<3,>=2.7.4
Requires-Dist: ruamel.yaml==0.18.6
Requires-Dist: pyfiglet==1.0.4
Requires-Dist: mcp>=0.4.2
Requires-Dist: langchain-mcp-adapters>=0.1.7
Requires-Dist: langchain-tavily>=0.1.0
Requires-Dist: genai-processors>=1.1.0
Requires-Dist: langchain-openai<0.4.0,>=0.3.0
Requires-Dist: langchain-ollama<0.4.0,>=0.3.0
Dynamic: license-file
